pycodeforces/__clients__.py
pycodeforces/__init__.py
pycodeforces/__processors__.py
pycodeforces/abc/__cobjects__.py
pycodeforces/abc/__endpoints__.py
pycodeforces/abc/__init__.py
pycodeforces/abc/__interactions__.py
pycodeforces/abc/__objects__.py
py_codeforce-1.3.dist-info/LICENSE
py_codeforce-1.3.dist-info/METADATA
py_codeforce-1.3.dist-info/WHEEL
py_codeforce-1.3.dist-info/top_level.txt
py_codeforce-1.3.dist-info/RECORD
