Metadata-Version: 2.1
Name: py-codeforce
Version: 1.3
Summary: Py-Codeforces is a high-performance and type-safe Python library designed for seamless interaction with Codeforces. It offers both asynchronous and synchronous client handlers, allowing developers to choose the appropriate method based on their requirements.
Home-page: https://github.com/halfstackpgr/py-codeforces
Author: Parth Mishra
Author-email: halfstackpgr <halfstackpgr@gmail.com>
License: GNU GENERAL PUBLIC LICENSE
Project-URL: Homepage, https://github.com/halfstackpgr/py-codeforces
Keywords: python,codeforces,api,wrapper,async,sync
Classifier: License :: OSI Approved :: GNU General Public License v3 (GPLv3)
Classifier: Programming Language :: Python
Classifier: Programming Language :: Python :: 3
Requires-Python: >=3.10
License-File: LICENSE
Requires-Dist: aiohttp
Requires-Dist: requests
Requires-Dist: msgspec
Requires-Dist: tomli ; python_version < "3.11"
Provides-Extra: dev
Requires-Dist: ruff ; extra == 'dev'
Requires-Dist: codespell ; extra == 'dev'
Requires-Dist: flake8 ; extra == 'dev'
Requires-Dist: mypy ; extra == 'dev'
